django_geoaddress-0.1.5.dist-info/licenses/LICENSE
djgeoaddress/__init__.py
djgeoaddress/apps.py
djgeoaddress/fields.py
djgeoaddress/rest_framework.py
djgeoaddress/urls.py
djgeoaddress/admin/__init__.py
djgeoaddress/admin/provider.py
djgeoaddress/admin/suggest.py
djgeoaddress/management/__init__.py
djgeoaddress/management/commands/__init__.py
djgeoaddress/management/commands/addresses_autocomplete.py
djgeoaddress/management/commands/reverse_geocode.py
djgeoaddress/management/commands/search_addresses.py
djgeoaddress/managers/__init__.py
djgeoaddress/managers/provider.py
djgeoaddress/managers/suggest.py
djgeoaddress/models/__init__.py
djgeoaddress/models/provider.py
djgeoaddress/models/suggest.py
djgeoaddress/views/__init__.py
djgeoaddress/views/index.py
djgeoaddress/views/provider.py
djgeoaddress/views/suggest.py
django_geoaddress-0.1.5.dist-info/METADATA
django_geoaddress-0.1.5.dist-info/WHEEL
django_geoaddress-0.1.5.dist-info/top_level.txt
django_geoaddress-0.1.5.dist-info/RECORD
