Metadata-Version: 2.4
Name: django-geoaddress
Version: 0.1.5
Summary: Django integration for address verification and geocoding. Provides Django fields, widgets, and admin integration for the geoaddress library.
Author-email: Hicinformatic <hicinformatic@gmail.com>
License: MIT
Project-URL: Homepage, https://github.com/hicinformatic/django-geoaddress
Project-URL: Repository, https://github.com/hicinformatic/django-geoaddress
Project-URL: Documentation, https://github.com/hicinformatic/django-geoaddress#readme
Project-URL: Issues, https://github.com/hicinformatic/django-geoaddress/issues
Keywords: django,geocoding,reverse-geocoding,address,geolocation,maps,django-fields,django-widgets,address-autocomplete,python
Classifier: Development Status :: 4 - Beta
Classifier: Intended Audience :: Developers
Classifier: Framework :: Django
Classifier: Framework :: Django :: 3.2
Classifier: Framework :: Django :: 4.0
Classifier: Framework :: Django :: 4.1
Classifier: Framework :: Django :: 4.2
Classifier: Framework :: Django :: 5.0
Classifier: Programming Language :: Python :: 3
Classifier: Programming Language :: Python :: 3.10
Classifier: Programming Language :: Python :: 3.11
Classifier: Programming Language :: Python :: 3.12
Classifier: Topic :: Software Development :: Libraries :: Python Modules
Classifier: Topic :: Internet :: WWW/HTTP :: Dynamic Content
Classifier: Topic :: Scientific/Engineering :: GIS
Requires-Python: >=3.10
License-File: LICENSE
Requires-Dist: Django>=3.2
Requires-Dist: geoaddress>=0.2.2
Requires-Dist: django-boosted>=0.1.0
Requires-Dist: django-providerkit>=0.1.0
Requires-Dist: django-virtualqueryset>=0.1.0
Provides-Extra: dev
Requires-Dist: pytest>=7.0; extra == "dev"
Requires-Dist: pytest-django>=4.5; extra == "dev"
Requires-Dist: ruff>=0.5; extra == "dev"
Requires-Dist: mypy>=1.0; extra == "dev"
Requires-Dist: django-stubs>=5.0.0; extra == "dev"
Requires-Dist: python-dotenv>=1.0; extra == "dev"
Provides-Extra: lint
Requires-Dist: ruff>=0.5.0; extra == "lint"
Requires-Dist: mypy>=1.0.0; extra == "lint"
Requires-Dist: semgrep>=1.0.0; extra == "lint"
Requires-Dist: pylint>=3.0.0; extra == "lint"
Provides-Extra: quality
Requires-Dist: radon>=6.0.0; extra == "quality"
Requires-Dist: vulture>=2.0.0; extra == "quality"
Requires-Dist: autoflake>=2.0.0; extra == "quality"
Provides-Extra: security
Requires-Dist: bandit>=1.7.0; extra == "security"
Requires-Dist: safety>=3.0.0; extra == "security"
Requires-Dist: pip-audit>=2.7.0; extra == "security"
Requires-Dist: semgrep>=1.0.0; extra == "security"
Dynamic: license-file
